{
  "project_info": {
    "project_number": "1045608501061",
    "project_id": "i-leaf-u",
    "storage_bucket": "i-leaf-u.firebasestorage.app"
  },
  "client": [
    {
      "client_info": {
        "mobilesdk_app_id": "1:1045608501061:android:8b83c2488b27303039782c",
        "android_client_info": {
          "package_name": "com.ileafu"
        }
      },
      "oauth_client": [],
      "api_key": [
        {
          "current_key": "AIzaSyDVNREZJRZdCl8j-W1DG5jrZgXEV-Lrthg"
        }
      ],
      "services": {
        "appinvite_service": {
          "other_platform_oauth_client": []
        }
      }
    }
  ],
  "configuration_version": "1"
}